[{"date":"2023-08-18T15:14:38.905Z","notUsedCount":5},{"date":"2023-08-28T07:02:57.413Z","notUsedCount":4},{"date":"2023-09-04T07:03:01.673Z","notUsedCount":4},{"date":"2023-09-18T07:03:03.049Z","notUsedCount":4},{"date":"2023-09-25T07:02:58.635Z","notUsedCount":4},{"date":"2023-10-02T07:02:53.743Z","notUsedCount":4},{"date":"2023-10-09T07:03:11.138Z","notUsedCount":4},{"date":"2023-10-16T07:02:53.422Z","notUsedCount":4},{"date":"2023-10-23T07:03:08.736Z","notUsedCount":9},{"date":"2023-10-30T07:02:50.823Z","notUsedCount":9},{"date":"2023-11-06T07:02:40.887Z","notUsedCount":9},{"date":"2023-11-13T07:03:01.013Z","notUsedCount":4},{"date":"2023-11-20T07:02:45.184Z","notUsedCount":4},{"date":"2023-11-27T07:02:42.595Z","notUsedCount":4},{"date":"2023-12-04T07:02:39.966Z","notUsedCount":4},{"date":"2023-12-11T07:02:44.477Z","notUsedCount":4},{"date":"2023-12-18T07:02:38.057Z","notUsedCount":4},{"date":"2023-12-25T07:02:33.510Z","notUsedCount":4},{"date":"2024-01-01T07:02:41.902Z","notUsedCount":4},{"date":"2024-01-08T07:02:35.109Z","notUsedCount":4},{"date":"2024-01-15T07:02:40.065Z","notUsedCount":4},{"date":"2024-01-22T07:02:44.788Z","notUsedCount":4},{"date":"2024-01-29T07:02:36.865Z","notUsedCount":4},{"date":"2024-02-05T07:02:47.393Z","notUsedCount":4},{"date":"2024-02-12T07:02:37.902Z","notUsedCount":4},{"date":"2024-02-19T07:02:37.753Z","notUsedCount":4},{"date":"2024-02-26T07:02:35.454Z","notUsedCount":5},{"date":"2024-03-04T07:21:44.997Z","notUsedCount":5},{"date":"2024-03-11T07:02:29.409Z","notUsedCount":5},{"date":"2024-03-18T07:02:30.453Z","notUsedCount":5},{"date":"2024-03-25T07:02:37.787Z","notUsedCount":5},{"date":"2024-04-01T07:02:30.055Z","notUsedCount":5},{"date":"2024-04-08T07:02:54.241Z","notUsedCount":5},{"date":"2024-04-15T07:02:27.682Z","notUsedCount":5},{"date":"2024-04-22T07:02:46.489Z","notUsedCount":5},{"date":"2024-04-29T07:02:41.934Z","notUsedCount":5},{"date":"2024-05-06T07:02:46.453Z","notUsedCount":5},{"date":"2024-05-13T07:02:49.635Z","notUsedCount":5},{"date":"2024-05-20T07:03:12.735Z","notUsedCount":5},{"date":"2024-05-27T07:03:33.363Z","notUsedCount":5}]